{
  "features": {
    "title": "Website Features",
    "sections": [
      {
        "title": "Home Page",
        "items": [
          "Navigation Bar: Sticky header with logo, brand name, and menu links",
          "Image Slider: Visual carousel showcasing featured games and activities",
          "Navigation Buttons: Quick access buttons to different sections",
          "Newly Added Games: Showcase of recently added games with preview cards",
          "Top Games Section: Display of most popular and trending games",
          "Footer Section: Contact information, social links, and quick navigation"
        ]
      },
      {
        "title": "Games Page",
        "items": [
          "Category Filtering System: Sidebar with game categories (Indoor, Outdoor, Kids, Family, etc.)",
          "Game Cards Grid: Responsive grid layout displaying all available games",
          "Advanced Filtering: Filter games by type, players, difficulty, and duration",
          "Search Functionality: Find specific games using search feature",
          "Quick View: Hover effects and quick information on game cards"
        ]
      },
      {
        "title": "Game Details Page",
        "items": [
          "Comprehensive Game Information: Complete details for each game",
          "Materials Required: List of all necessary items with icons",
          "Step-by-Step Instructions: Detailed how-to-play guide",
          "Time & Player Info: Duration and player count requirements",
          "Difficulty Rating: Visual indicators for game complexity",
          "Download Options: Printable instructions and rule sheets",
          "Related Games: Suggestions for similar games"
        ]
      },
      {
        "title": "About Page",
        "items": [
          "Company Information: Background and mission of PlayfulOutings",
          "Team Introduction: Meet the creators and developers",
          "Vision & Values: Core principles and future goals",
          "Achievements: Milestones and user statistics"
        ]
      },
      {
        "title": "Contact Page",
        "items": [
          "Contact Form: User inquiry form with validation",
          "Location Map: Interactive map showing business location",
          "Contact Details: Phone, email, and physical address",
          "Social Media Links: Direct links to social platforms",
          "FAQ Section: Frequently asked questions and answers"
        ]
      }
    ]
  }
}